<?xml version="1.0" encoding="UTF-8"?>

<annotation> 
  <folder>Lyra用</folder>  
  <filename>Galaxy_0491.jpg</filename>  
  <path>src/main/resources/data/Images/Galaxy_0491.jpg</path>  
  <source> 
    <database>Unknown</database> 
  </source>  
  <size> 
    <width>416</width>  
    <height>416</height>  
    <depth>3</depth> 
  </size>  
  <segmented>0</segmented>  
  <object> 
    <name>Lyra</name>  
    <pose>Unspecified</pose>  
    <truncated>0</truncated>  
    <difficult>0</difficult>  
    <bndbox> 
      <xmin>278</xmin>  
      <ymin>124</ymin>  
      <xmax>299</xmax>  
      <ymax>147</ymax> 
    </bndbox> 
  </object>  
  <object> 
    <name>Lyra</name>  
    <pose>Unspecified</pose>  
    <truncated>0</truncated>  
    <difficult>0</difficult>  
    <bndbox> 
      <xmin>308</xmin>  
      <ymin>120</ymin>  
      <xmax>325</xmax>  
      <ymax>139</ymax> 
    </bndbox> 
  </object>  
  <object> 
    <name>Lyra</name>  
    <pose>Unspecified</pose>  
    <truncated>0</truncated>  
    <difficult>0</difficult>  
    <bndbox> 
      <xmin>299</xmin>  
      <ymin>73</ymin>  
      <xmax>318</xmax>  
      <ymax>93</ymax> 
    </bndbox> 
  </object>  
  <object> 
    <name>Lyra</name>  
    <pose>Unspecified</pose>  
    <truncated>0</truncated>  
    <difficult>0</difficult>  
    <bndbox> 
      <xmin>330</xmin>  
      <ymin>64</ymin>  
      <xmax>343</xmax>  
      <ymax>86</ymax> 
    </bndbox> 
  </object>  
  <object> 
    <name>Lyra</name>  
    <pose>Unspecified</pose>  
    <truncated>0</truncated>  
    <difficult>0</difficult>  
    <bndbox> 
      <xmin>331</xmin>  
      <ymin>36</ymin>  
      <xmax>349</xmax>  
      <ymax>57</ymax> 
    </bndbox> 
  </object>  
  <object> 
    <name>Lyra</name>  
    <pose>Unspecified</pose>  
    <truncated>0</truncated>  
    <difficult>0</difficult>  
    <bndbox> 
      <xmin>348</xmin>  
      <ymin>48</ymin>  
      <xmax>371</xmax>  
      <ymax>75</ymax> 
    </bndbox> 
  </object> 
</annotation>
